fsfs/__init__.py
fsfs/__main__.py
fsfs/_compat.py
fsfs/_search.py
fsfs/api.py
fsfs/channels.py
fsfs/cli.py
fsfs/constants.py
fsfs/factory.py
fsfs/lockfile.py
fsfs/models.py
fsfs/policy.py
fsfs/types.py
fsfs/util.py
fsfs/vendor/__init__.py
fsfs/vendor/yaml/LICENSE
fsfs/vendor/yaml/__init__.py
fsfs/vendor/yaml/yaml2/__init__.py
fsfs/vendor/yaml/yaml2/composer.py
fsfs/vendor/yaml/yaml2/constructor.py
fsfs/vendor/yaml/yaml2/cyaml.py
fsfs/vendor/yaml/yaml2/dumper.py
fsfs/vendor/yaml/yaml2/emitter.py
fsfs/vendor/yaml/yaml2/error.py
fsfs/vendor/yaml/yaml2/events.py
fsfs/vendor/yaml/yaml2/loader.py
fsfs/vendor/yaml/yaml2/nodes.py
fsfs/vendor/yaml/yaml2/parser.py
fsfs/vendor/yaml/yaml2/reader.py
fsfs/vendor/yaml/yaml2/representer.py
fsfs/vendor/yaml/yaml2/resolver.py
fsfs/vendor/yaml/yaml2/scanner.py
fsfs/vendor/yaml/yaml2/serializer.py
fsfs/vendor/yaml/yaml2/tokens.py
fsfs/vendor/yaml/yaml3/__init__.py
fsfs/vendor/yaml/yaml3/composer.py
fsfs/vendor/yaml/yaml3/constructor.py
fsfs/vendor/yaml/yaml3/cyaml.py
fsfs/vendor/yaml/yaml3/dumper.py
fsfs/vendor/yaml/yaml3/emitter.py
fsfs/vendor/yaml/yaml3/error.py
fsfs/vendor/yaml/yaml3/events.py
fsfs/vendor/yaml/yaml3/loader.py
fsfs/vendor/yaml/yaml3/nodes.py
fsfs/vendor/yaml/yaml3/parser.py
fsfs/vendor/yaml/yaml3/reader.py
fsfs/vendor/yaml/yaml3/representer.py
fsfs/vendor/yaml/yaml3/resolver.py
fsfs/vendor/yaml/yaml3/scanner.py
fsfs/vendor/yaml/yaml3/serializer.py
fsfs/vendor/yaml/yaml3/tokens.py
fsfs-0.3.1.dist-info/LICENSE
fsfs-0.3.1.dist-info/METADATA
fsfs-0.3.1.dist-info/WHEEL
fsfs-0.3.1.dist-info/entry_points.txt
fsfs-0.3.1.dist-info/top_level.txt
fsfs-0.3.1.dist-info/RECORD
